[
  {
    "nanoid": "a2vebKp6rSzqyQ",
    "name": "30A Loomered TV",
    "iptv_urls": [
      "https://30a-tv.com/loomer.m3u8"
    ],
    "youtube_urls": [],
    "language": "eng",
    "country": "us",
    "isGeoBlocked": false
  },
  {
    "nanoid": "7ww4XqjlIRbeax",
    "name": "Asahi: Documentary",
    "iptv_urls": [],
    "youtube_urls": [
      "https://www.youtube-nocookie.com/embed/ZDuY5ZF-hhc"
    ],
    "language": "jpn",
    "country": "jp",
    "isGeoBlocked": false
  },
  {
    "nanoid": "eNsC6GxX1XiJq8",
    "name": "Asharq Documentary",
    "iptv_urls": [
      "https://svs.itworkscdn.net/asharqdocumentarylive/asharqdocumentary.smil/playlist_dvr.m3u8"
    ],
    "youtube_urls": [],
    "language": "ara",
    "country": "sa",
    "isGeoBlocked": false
  },
  {
    "nanoid": "smXRAxpQSslGHk",
    "name": "AXS TV NOW",
    "iptv_urls": [
      "https://dikcfc9915kp8.cloudfront.net/hls/main.m3u8",
      "https://dikcfc9915kp8.cloudfront.net/hls/1080p/playlist.m3u8"
    ],
    "youtube_urls": [],
    "language": "eng",
    "country": "us",
    "isGeoBlocked": false
  },
  {
    "nanoid": "BKprRPWc9ugskl",
    "name": "Backstage",
    "iptv_urls": [
      "https://fuse-backstage-xumo.amagi.tv/playlist.m3u8"
    ],
    "youtube_urls": [],
    "language": "eng",
    "country": "us",
    "isGeoBlocked": true
  },
  {
    "nanoid": "hTeaugAEZXJDNG",
    "name": "Banijay History: Hitler's Countdown to War",
    "iptv_urls": [],
    "youtube_urls": [
      "https://www.youtube-nocookie.com/embed/pMXdhpccmJo"
    ],
    "language": "eng",
    "country": "uk",
    "isGeoBlocked": false
  },
  {
    "nanoid": "WH7adDfFfMrDqi",
    "name": "Bloomberg Originals",
    "iptv_urls": [
      "https://d7ec4f6950ed4c6d946e497bd44db7ef.mediatailor.us-east-1.amazonaws.com/v1/master/44f73ba4d03e9607dcd9bebdcb8494d86964f1d8/RakutenTV-eu_QuickTake-1/playlist.m3u8"
    ],
    "youtube_urls": [
      "https://www.youtube-nocookie.com/embed/OlUMDZchivQ"
    ],
    "language": "eng",
    "country": "us",
    "isGeoBlocked": false
  },
  {
    "nanoid": "zV7a20HW4WTHRY",
    "name": "BritBox Mysteries",
    "iptv_urls": [
      "https://aegis-cloudfront-1.tubi.video/647bc22c-e1bb-4bca-afaf-5de99cbc2286/playlist.m3u8"
    ],
    "youtube_urls": [],
    "language": "eng",
    "country": "us",
    "isGeoBlocked": false
  },
  {
    "nanoid": "u673t64oVwJcTF",
    "name": "CGTN Documentary",
    "iptv_urls": [
      "https://amg00405-rakutentv-cgtndocumentary-rakuten-0ql8j.amagi.tv/master.m3u8",
      "https://english-livebkali.cgtn.com/live/doccgtn.m3u8"
    ],
    "youtube_urls": [],
    "language": "eng",
    "country": "cn",
    "isGeoBlocked": false
  },
  {
    "nanoid": "itmATVZa5Ggr1u",
    "name": "Click TV (Coronel)",
    "iptv_urls": [
      "https://v2.tustreaming.cl/clicktv/playlist.m3u8"
    ],
    "youtube_urls": [],
    "language": "spa",
    "country": "cl",
    "isGeoBlocked": false
  },
  {
    "nanoid": "b3SY5CGeJGKaQq",
    "name": "CNA Insider",
    "iptv_urls": [],
    "youtube_urls": [
      "https://www.youtube-nocookie.com/embed/fSUMKrxPEd8"
    ],
    "language": "eng",
    "country": "sg",
    "isGeoBlocked": false
  },
  {
    "nanoid": "sm6jSJZU2R13Dv",
    "name": "Court TV",
    "iptv_urls": [
      "https://content.uplynk.com/channel/6c0bd0f94b1d4526a98676e9699a10ef.m3u8",
      "https://apollo.production-public.tubi.io/live/ac-court-tv.m3u8",
      "https://scripps-courttv-2-us.xumo.wurl.tv/playlist.m3u8"
    ],
    "youtube_urls": [],
    "language": "eng",
    "country": "us",
    "isGeoBlocked": false
  },
  {
    "nanoid": "jAekBDqlLERFF0",
    "name": "Dateline 24/7",
    "iptv_urls": [
      "https://apollo.production-public.tubi.io/live/ac-dateline.m3u8",
      "https://dz59iptwz5rxs.cloudfront.net/live/master.m3u8"
    ],
    "youtube_urls": [],
    "language": "eng",
    "country": "us",
    "isGeoBlocked": false
  },
  {
    "nanoid": "FQVKNsI92Y63Vf",
    "name": "Dokusat",
    "iptv_urls": [
      "https://muc3.iptv-playoutcenter.de/dokusat/dokusat1/playlist.m3u8"
    ],
    "youtube_urls": [],
    "language": "deu",
    "country": "de",
    "isGeoBlocked": false
  },
  {
    "nanoid": "nFh3xqtwlLRiFW",
    "name": "Ecovisión",
    "iptv_urls": [
      "https://streaming.grupomediosdelnorte.com:19360/ecovision/ecovision.m3u8"
    ],
    "youtube_urls": [],
    "language": "spa",
    "country": "do",
    "isGeoBlocked": false
  },
  {
    "nanoid": "fhjZefrsTYtZby",
    "name": "FBI Files",
    "iptv_urls": [
      "https://apollo.production-public.tubi.io/live/ac-the-fbi-files.m3u8"
    ],
    "youtube_urls": [],
    "language": "eng",
    "country": "uk",
    "isGeoBlocked": false
  },
  {
    "nanoid": "ok1XbdadbIAXgd",
    "name": "Francophonie24",
    "iptv_urls": [
      "https://5421175365ea3.streamlock.net/live/smil:switch.smil/playlist.m3u8"
    ],
    "youtube_urls": [],
    "language": "fra",
    "country": "fr",
    "isGeoBlocked": false
  },
  {
    "nanoid": "97DWduUX5Hf0aj",
    "name": "FUSION TV",
    "iptv_urls": [
      "https://edge20.vedge.infomaniak.com/livecast/ik:fusiontv/manifest.m3u8"
    ],
    "youtube_urls": [],
    "language": "fra",
    "country": "mq",
    "isGeoBlocked": false
  },
  {
    "nanoid": "GOMdLvvyu3y5ss",
    "name": "GZT",
    "iptv_urls": [
      "https://mn-nl.mncdn.com/gzttv/gzttv/playlist.m3u8"
    ],
    "youtube_urls": [],
    "language": "tur",
    "country": "tr",
    "isGeoBlocked": false
  },
  {
    "nanoid": "YDIi3VBX7D7fKC",
    "name": "La 2 Catalunya",
    "iptv_urls": [
      "https://ztnr.rtve.es/ztnr/3987218.m3u8",
      "https://rtvelivestream.akamaized.net/rtvesec/cat/la2_cat_main_dvr.m3u8"
    ],
    "youtube_urls": [],
    "language": "cat",
    "country": "es",
    "isGeoBlocked": false
  },
  {
    "nanoid": "feuZPyWhX6la0P",
    "name": "Law & Crime",
    "iptv_urls": [
      "https://a-cdn.klowdtv.com/live3/law_720p/playlist.m3u8",
      "https://cdn.lawandcrime.net/rewind/playlist.m3u8"
    ],
    "youtube_urls": [],
    "language": "eng",
    "country": "us",
    "isGeoBlocked": false
  },
  {
    "nanoid": "AbcJxYxf3cyf3H",
    "name": "NatureTime",
    "iptv_urls": [
      "https://shls-live-ak.akamaized.net/out/v1/b06a89a463764d3688cda337d40dc5bf/index.m3u8"
    ],
    "youtube_urls": [],
    "language": "spa",
    "country": "es",
    "isGeoBlocked": false
  },
  {
    "nanoid": "OMzjODF6Uqhu43",
    "name": "Nova TV Agrotour",
    "iptv_urls": [
      "https://video01.kshost.com.br/marcelo6682/marcelo6682/playlist.m3u8"
    ],
    "youtube_urls": [],
    "language": "por",
    "country": "br",
    "isGeoBlocked": false
  },
  {
    "nanoid": "gOuwLzCKrgxJvt",
    "name": "Reelz",
    "iptv_urls": [
      "https://bcovlive-a.akamaihd.net/rc21a8bc6455344c699a06e9220fe2748/us-west-2/5245389775001/playlist.m3u8",
      "https://apollo.production-public.tubi.io/live/ac-reelz.m3u8"
    ],
    "youtube_urls": [],
    "language": "eng",
    "country": "us",
    "isGeoBlocked": false
  },
  {
    "nanoid": "VMF9bz9jysLZtk",
    "name": "RT Documentary English",
    "iptv_urls": [
      "https://rt-rtd.rttv.com/dvr/rtdoc/playlist.m3u8",
      "https://rt-rtd.rttv.com/live/rtdoc/playlist.m3u8"
    ],
    "youtube_urls": [],
    "language": "eng",
    "country": "ru",
    "isGeoBlocked": false
  },
  {
    "nanoid": "0mulGVhtSW9kDC",
    "name": "RT Documentary Russian",
    "iptv_urls": [
      "https://hls.rt.com/hls/rtdru.m3u8",
      "https://streaming.televizor-24-tochka.ru/live/554.m3u8"
    ],
    "youtube_urls": [],
    "language": "rus",
    "country": "ru",
    "isGeoBlocked": false
  },
  {
    "nanoid": "tT2v90JHj1tcan",
    "name": "The Nest",
    "iptv_urls": [
      "https://content.uplynk.com/channel/b468fd41b60840579668c42c096a4103.m3u8"
    ],
    "youtube_urls": [],
    "language": "eng",
    "country": "us",
    "isGeoBlocked": false
  },
  {
    "nanoid": "0DOlfiRKChwd21",
    "name": "Wedo Big Stories",
    "iptv_urls": [
      "https://weyyak-live.akamaized.net/wedo_big_stories/index.m3u8"
    ],
    "youtube_urls": [],
    "language": "eng",
    "country": "ch",
    "isGeoBlocked": false
  }
]