[
  {
    "nanoid": "MHC3rqs2EaQPud",
    "name": "DanmarkC TV",
    "iptv_urls": [],
    "youtube_urls": [
      "https://www.youtube-nocookie.com/embed/myKvlNGAz2o"
    ],
    "language": "dan",
    "country": "dk",
    "isGeoBlocked": false
  },
  {
    "nanoid": "V5LLT8Xso7GEeT",
    "name": "DRTV",
    "iptv_urls": [
      "https://drlivedrtvahls.akamaized.net/hls/live/2113613/drlivedrtva/master.m3u8"
    ],
    "youtube_urls": [],
    "language": "dan",
    "country": "dk",
    "isGeoBlocked": false
  }
]