[
  {
    "nanoid": "wbP1yV7MoOQbP3",
    "name": "Hispania TV",
    "iptv_urls": [
      "https://www.streaming507.net:19360/hispaniamediatv/hispaniamediatv.m3u8"
    ],
    "youtube_urls": [],
    "language": "spa",
    "country": "pa",
    "isGeoBlocked": false
  },
  {
    "nanoid": "1s0ZBPgnFvrJev",
    "name": "MINFAV TV",
    "iptv_urls": [
      "https://video.misistemareseller.com/minfavtv/minfavtv/playlist.m3u8"
    ],
    "youtube_urls": [],
    "language": "spa",
    "country": "pa",
    "isGeoBlocked": false
  },
  {
    "nanoid": "3sv3KZigllTlNS",
    "name": "Pindin TV",
    "iptv_urls": [
      "https://sistemastr.tropicalmoonmedia.com/live/C0F6BECADC057D029E107B68CCEBD042/37.m3u8"
    ],
    "youtube_urls": [],
    "language": "spa",
    "country": "pa",
    "isGeoBlocked": false
  },
  {
    "nanoid": "NrKrfT28f0zHMn",
    "name": "Planet 100.9 FM",
    "iptv_urls": [
      "https://streamlov.alsolnet.com/planet1009fm/live/playlist.m3u8"
    ],
    "youtube_urls": [],
    "language": "spa",
    "country": "pa",
    "isGeoBlocked": false
  },
  {
    "nanoid": "dNZF0BG3ys3ZI5",
    "name": "Radio Ancón",
    "iptv_urls": [
      "https://www.streaming507.net:19360/anconvideo/anconvideo.m3u8"
    ],
    "youtube_urls": [],
    "language": "spa",
    "country": "pa",
    "isGeoBlocked": false
  },
  {
    "nanoid": "mfsWJwtwhG3h3c",
    "name": "Radio Hogar",
    "iptv_urls": [
      "https://www.streaming507.net:19360/videoradiohogar/videoradiohogar.m3u8"
    ],
    "youtube_urls": [],
    "language": "spa",
    "country": "pa",
    "isGeoBlocked": false
  },
  {
    "nanoid": "DC89BKzT53NaL5",
    "name": "Somos Cultura TV",
    "iptv_urls": [
      "https://sistemastr.tropicalmoonmedia.com/live/B1A9C28E12916F32510C5CE5B80B58EE/5.m3u8"
    ],
    "youtube_urls": [],
    "language": "spa",
    "country": "pa",
    "isGeoBlocked": false
  }
]